label_train/__init__.py
label_train/__main__.py
label_train/main.py
labeltrain-4.0.6.dist-info/licenses/LICENSE
labeltrain-4.0.6.dist-info/METADATA
labeltrain-4.0.6.dist-info/WHEEL
labeltrain-4.0.6.dist-info/entry_points.txt
labeltrain-4.0.6.dist-info/top_level.txt
labeltrain-4.0.6.dist-info/RECORD
